dedupe/convenience.py
dedupe/canopy_index.py
dedupe/predicate_functions.py
dedupe/cpredicates.cpython-313-darwin.so
dedupe/predicates.py
dedupe/clustering.py
dedupe/_typing.py
dedupe/index.py
dedupe/datamodel.py
dedupe/__init__.py
dedupe/core.py
dedupe/api.py
dedupe/canonical.py
dedupe/labeler.py
dedupe/blocking.py
dedupe/levenshtein.py
dedupe/backport.py
dedupe/py.typed
dedupe/serializer.py
dedupe/cpredicates.c
dedupe/branch_and_bound.py
dedupe/tfidf.py
dedupe/cpredicates.pyx
dedupe/training.py
dedupe/variables/exists.py
dedupe/variables/interaction.py
dedupe/variables/__init__.py
dedupe/variables/latlong.py
dedupe/variables/exact.py
dedupe/variables/categorical_type.py
dedupe/variables/string.py
dedupe/variables/set.py
dedupe/variables/base.py
dedupe/variables/price.py
dedupe-3.0.3.dist-info/RECORD
dedupe-3.0.3.dist-info/LICENSE
dedupe-3.0.3.dist-info/WHEEL
dedupe-3.0.3.dist-info/top_level.txt
dedupe-3.0.3.dist-info/METADATA
