Metadata-Version: 2.1
Name: dedupe
Version: 3.0.3
Summary: A python library for accurate and scaleable data deduplication and entity-resolution
Author-email: Forest Gregg <fgregg@datamade.us>
License: The MIT License (MIT)
Project-URL: Homepage, https://github.com/dedupeio/dedupe
Project-URL: Issues, https://github.com/dedupeio/dedupe/issues
Project-URL: Documentation, https://docs.dedupe.io/en/latest/
Project-URL: Examples, https://github.com/dedupeio/dedupe-examples
Project-URL: Twitter, https://twitter.com/DedupeIo
Project-URL: Changelog, https://github.com/dedupeio/dedupe/blob/main/CHANGELOG.md
Project-URL: MailingList, https://groups.google.com/forum/#!forum/open-source-deduplication
Classifier: Development Status :: 4 - Beta
Classifier: Intended Audience :: Developers
Classifier: Intended Audience :: Science/Research
Classifier: License :: OSI Approved :: MIT License
Classifier: Natural Language :: English
Classifier: Operating System :: MacOS :: MacOS X
Classifier: Operating System :: Microsoft :: Windows
Classifier: Operating System :: POSIX
Classifier: Programming Language :: Cython
Classifier: Programming Language :: Python :: 3
Classifier: Topic :: Software Development :: Libraries :: Python Modules
Classifier: Topic :: Scientific/Engineering
Classifier: Topic :: Scientific/Engineering :: Information Analysis
Requires-Python: >=3.8
License-File: LICENSE
Requires-Dist: scikit-learn
Requires-Dist: affinegap>=1.3
Requires-Dist: categorical-distance>=1.9
Requires-Dist: numpy>=1.20
Requires-Dist: doublemetaphone
Requires-Dist: highered>=0.2.0
Requires-Dist: simplecosine>=1.2
Requires-Dist: haversine>=0.4.1
Requires-Dist: BTrees>=4.1.4
Requires-Dist: zope.index
Requires-Dist: dedupe_Levenshtein_search
